numpy_turtle/__init__.py
numpy_turtle/l_system.py
numpy_turtle/numpy_turtle.py
numpy_turtle-0.3.dist-info/METADATA
numpy_turtle-0.3.dist-info/WHEEL
numpy_turtle-0.3.dist-info/licenses/LICENSE
numpy_turtle-0.3.dist-info/RECORD
