Metadata-Version: 2.4
Name: numpy_turtle
Version: 0.3
Summary: Turtle graphics with NumPy
Author-email: Joren Hammudoglu <jhammudoglu@gmail.com>
License-Expression: MIT
License-File: LICENSE
Classifier: Development Status :: 5 - Production/Stable
Classifier: License :: OSI Approved :: MIT License
Classifier: Operating System :: OS Independent
Classifier: Programming Language :: Python :: 3.11
Classifier: Programming Language :: Python :: 3.12
Classifier: Programming Language :: Python :: 3.13
Classifier: Typing :: Typed
Requires-Python: >=3.11
Requires-Dist: numpy>=1.25
Requires-Dist: scikit-image>=0.20
